{"nodes": [{"id": "prd_p_emr_rj_asm_v1_0_asesmen_rawat_jalan", "label": "Asesmen Rawat Jalan (Keperawatan & Dokter)", "file_type": "document", "source_file": "other_prd(prd_dari_google_drive)/Pelayanan (.md)/PRD-Asesmen-Rawat-Jalan-v1_0.md"}, {"id": "prd_dashboard_pelayanan_rj", "label": "PRD Dashboard Pelayanan Rawat Jalan", "file_type": "document", "source_file": "other_prd(prd_dari_google_drive)/Pelayanan (.md)/PRD-Asesmen-Rawat-Jalan-v1_0.md"}, {"id": "prd_konsul_internal_rujuk_internal", "label": "PRD Konsul Internal vs Rujuk Internal", "file_type": "document", "source_file": "other_prd(prd_dari_google_drive)/Pelayanan (.md)/PRD-Asesmen-Rawat-Jalan-v1_0.md"}], "edges": [{"source": "prd_p_emr_rj_asm_v1_0_asesmen_rawat_jalan", "target": "prd_dashboard_pelayanan_rj", "relation": "references", "confidence": "EXTRACTED", "confidence_score": 1.0, "source_file": "other_prd(prd_dari_google_drive)/Pelayanan (.md)/PRD-Asesmen-Rawat-Jalan-v1_0.md"}, {"source": "prd_p_emr_rj_asm_v1_0_asesmen_rawat_jalan", "target": "prd_konsul_internal_rujuk_internal", "relation": "references", "confidence": "EXTRACTED", "confidence_score": 1.0, "source_file": "other_prd(prd_dari_google_drive)/Pelayanan (.md)/PRD-Asesmen-Rawat-Jalan-v1_0.md"}], "hyperedges": [{"id": "emr_foundation_v2", "label": "Neurovi v2 EMR Foundation", "nodes": ["prd_p_emr_rj_asm_v1_0_asesmen_rawat_jalan", "prd_p_apigd_v2_0_asesmen_perawat_igd", "prd_pm_rhb_v2_0_asesmen_penunjang_medis_rehab"], "relation": "participate_in", "confidence": "INFERRED", "confidence_score": 0.85, "source_file": "other_prd(prd_dari_google_drive)/Pelayanan (.md)/PRD-Asesmen-Rawat-Jalan-v1_0.md"}]}